requests_throttler/__init__.py
requests_throttler/example.py
requests_throttler/exceptions.py
requests_throttler/settings.py
requests_throttler/throttled_request.py
requests_throttler/throttler.py
requests_throttler/utils.py
requests_throttler/tests/__init__.py
requests_throttler/tests/test_base_throttler.py
requests_throttler/tests/test_throttled_request.py
requests_throttler/tests/test_timer.py
RequestsThrottler-0.2.5.dist-info/LICENSE
RequestsThrottler-0.2.5.dist-info/METADATA
RequestsThrottler-0.2.5.dist-info/WHEEL
RequestsThrottler-0.2.5.dist-info/top_level.txt
RequestsThrottler-0.2.5.dist-info/RECORD
