Metadata-Version: 2.1
Name: RequestsThrottler
Version: 0.2.5
Summary: Python HTTP requests throttler
Home-page: https://github.com/se7entyse7en/requests-throttler
Author: Lou Marvin Caraig
Author-email: loumarvincaraig@gmail.com
License: Apache 2.0
Platform: UNKNOWN
Classifier: Development Status :: 4 - Beta
Classifier: Environment :: Web Environment
Classifier: Intended Audience :: Developers
Classifier: Intended Audience :: System Administrators
Classifier: License :: OSI Approved :: Apache Software License
Classifier: Natural Language :: English
Classifier: Programming Language :: Python
Classifier: Topic :: Internet
Classifier: Topic :: Internet :: WWW/HTTP
Requires-Dist: requests (>=2.1.0)
Requires-Dist: futures (>=2.1.5)
